pelican/plugins/captions/__init__.py
pelican/plugins/captions/captions.py
pelican/plugins/captions/test_captions.py
pelican_captions-0.4.1.dist-info/LICENSE
pelican_captions-0.4.1.dist-info/METADATA
pelican_captions-0.4.1.dist-info/WHEEL
pelican_captions-0.4.1.dist-info/RECORD
