Metadata-Version: 2.1
Name: pelican-captions
Version: 0.4.1
Summary: Add captions and labels to figures, tables and code blocks.
Home-page: https://github.com/f-koehler/pelican-captions
License: AGPL-3.0
Keywords: pelican,plugin
Author: Fabian Köhler
Author-email: fabian.koehler@protonmail.ch
Requires-Python: >=3.10,<4.0
Classifier: Development Status :: 3 - Alpha
Classifier: Environment :: Console
Classifier: Framework :: Pelican
Classifier: Framework :: Pelican :: Plugins
Classifier: Intended Audience :: End Users/Desktop
Classifier: License :: OSI Approved :: GNU Affero General Public License v3
Classifier: Operating System :: OS Independent
Classifier: Programming Language :: Python :: 3
Classifier: Programming Language :: Python :: 3.10
Classifier: Programming Language :: Python :: 3.11
Classifier: Topic :: Internet :: WWW/HTTP
Classifier: Topic :: Software Development :: Libraries :: Python Modules
Provides-Extra: markdown
Requires-Dist: beautifulsoup4 (>=4.9.3,<5.0.0)
Requires-Dist: markdown (>=3.2.2,<4.0.0) ; extra == "markdown"
Requires-Dist: pelican (>=4.5,<5.0)
Project-URL: Documentation, https://docs.getpelican.com
Project-URL: Funding, https://donate.getpelican.com/
Project-URL: Issue Tracker, https://github.com/f-koehler/pelican-captions/issues
Project-URL: Repository, https://github.com/f-koehler/pelican-captions
